planetpy/__init__.py
planetpy/constants.py
planetpy/factsheet_parse.py
planetpy/io.py
planetpy/utils.py
planetpy/pdstools/__init__.py
planetpy/pdstools/atlas.py
planetpy/pdstools/cassini.py
planetpy/pdstools/cli.py
planetpy/pdstools/indices.py
planetpy/pdstools/opusapi.py
planetpy/pdstools/data/__init__.py
planetpy/pdstools/data/indices_paths.toml
planetpy/spicekernels/__init__.py
planetpy/spicekernels/cassini.py
planetpy/spicekernels/general.py
planetpy-0.4.6.dist-info/AUTHORS.rst
planetpy-0.4.6.dist-info/LICENSE
planetpy-0.4.6.dist-info/METADATA
planetpy-0.4.6.dist-info/WHEEL
planetpy-0.4.6.dist-info/entry_points.txt
planetpy-0.4.6.dist-info/top_level.txt
planetpy-0.4.6.dist-info/RECORD
