Metadata-Version: 2.1
Name: planetpy
Version: 0.4.6
Summary: Python module to support analysis of planetary data.
Home-page: https://github.com/michaelaye/planetpy
Author: K.-Michael Aye
Author-email: kmichael.aye@gmail.com
License: ISC
Keywords: planetpy
Platform: UNKNOWN
Classifier: Development Status :: 2 - Pre-Alpha
Classifier: Intended Audience :: Science/Research
Classifier: License :: OSI Approved :: ISC License (ISCL)
Classifier: Natural Language :: English
Classifier: Programming Language :: Python :: 3
Classifier: Programming Language :: Python :: 3.5
Requires-Dist: pandas
Requires-Dist: pvl
Requires-Dist: tqdm
Requires-Dist: click
Requires-Dist: toml
Requires-Dist: requests
Requires-Dist: importlib-resources
